clismo/__init__.py
clismo/automata/__init__.py
clismo/automata/automata.py
clismo/automata/state.py
clismo/automata/transition.py
clismo/builtin/__init__.py
clismo/builtin/cs_built_in_functions.py
clismo/compiler/__init__.py
clismo/compiler/generic_ast.py
clismo/compiler/grammar.py
clismo/compiler/grammar_ops.py
clismo/compiler/parser_manager.py
clismo/compiler/parsers/__init__.py
clismo/compiler/parsers/lr1_parser.py
clismo/compiler/parsers/lritem.py
clismo/compiler/parsers/parser.py
clismo/compiler/terminal_set.py
clismo/compiler/tokenizer.py
clismo/cs_ast.py
clismo/cs_builders.py
clismo/cs_grammar.gm
clismo/cs_lr1_table
clismo/cs_tokenizer.py
clismo/csre.py
clismo/exceptions.py
clismo/ia/genetic_alg.py
clismo/lang/__init__.py
clismo/lang/context.py
clismo/lang/type.py
clismo/lang/visitor.py
clismo/main.py
clismo/optimization/__init__.py
clismo/optimization/client_server_optimizer.py
clismo/optimization/fuzzy_opt_classifier.py
clismo/optimization/optimizer.py
clismo/sim/__init__.py
clismo/sim/client.py
clismo/sim/client_server_model.py
clismo/sim/optimizable_obj.py
clismo/sim/server.py
clismo/sim/simulation.py
clismo/sim/step.py
clismo/visitors/__init__.py
clismo/visitors/eval_visitor.py
clismo/visitors/semantic_checker.py
clismo/visitors/type_builder.py
clismo-0.1.4.dist-info/entry_points.txt
clismo-0.1.4.dist-info/LICENSE
clismo-0.1.4.dist-info/WHEEL
clismo-0.1.4.dist-info/METADATA
clismo-0.1.4.dist-info/RECORD
